odoo/addons/web_widget_plotly_chart/README.rst
odoo/addons/web_widget_plotly_chart/__init__.py
odoo/addons/web_widget_plotly_chart/__manifest__.py
odoo/addons/web_widget_plotly_chart/i18n/ca.po
odoo/addons/web_widget_plotly_chart/i18n/da.po
odoo/addons/web_widget_plotly_chart/i18n/es.po
odoo/addons/web_widget_plotly_chart/i18n/pt_BR.po
odoo/addons/web_widget_plotly_chart/i18n/web_widget_plotly_chart.pot
odoo/addons/web_widget_plotly_chart/readme/CONTRIBUTORS.rst
odoo/addons/web_widget_plotly_chart/readme/CREDITS.rst
odoo/addons/web_widget_plotly_chart/readme/DESCRIPTION.rst
odoo/addons/web_widget_plotly_chart/readme/INSTALL.rst
odoo/addons/web_widget_plotly_chart/readme/USAGE.rst
odoo/addons/web_widget_plotly_chart/static/description/example.png
odoo/addons/web_widget_plotly_chart/static/description/icon.png
odoo/addons/web_widget_plotly_chart/static/description/index.html
odoo/addons/web_widget_plotly_chart/static/lib/plotly/plotly-latest.min.js
odoo/addons/web_widget_plotly_chart/static/src/js/widget_plotly.js
odoo/addons/web_widget_plotly_chart/views/web_widget_plotly_chart.xml
odoo12_addon_web_widget_plotly_chart-12.0.1.0.1.dist-info/METADATA
odoo12_addon_web_widget_plotly_chart-12.0.1.0.1.dist-info/WHEEL
odoo12_addon_web_widget_plotly_chart-12.0.1.0.1.dist-info/top_level.txt
odoo12_addon_web_widget_plotly_chart-12.0.1.0.1.dist-info/RECORD
